patchkit/__init__.py
patchkit/__main__.py
patchkit/cli.py
patchkit-0.2.0.dist-info/licenses/LICENSE
patchkit-0.2.0.dist-info/METADATA
patchkit-0.2.0.dist-info/WHEEL
patchkit-0.2.0.dist-info/top_level.txt
patchkit-0.2.0.dist-info/RECORD
