Metadata-Version: 2.4
Name: patchkit
Version: 0.2.0
Summary: A toolkit to apply and revert patches on models.
Author: patchkit contributors
License:                                  Apache License
Project-URL: Homepage, https://github.com/44670/patchkit
Project-URL: Repository, https://github.com/44670/patchkit
Project-URL: Issues, https://github.com/44670/patchkit/issues
Classifier: Development Status :: 3 - Alpha
Classifier: Intended Audience :: Developers
Classifier: License :: OSI Approved :: Apache Software License
Classifier: Programming Language :: Python :: 3
Classifier: Programming Language :: Python :: 3.8
Classifier: Programming Language :: Python :: 3.9
Classifier: Programming Language :: Python :: 3.10
Classifier: Programming Language :: Python :: 3.11
Classifier: Programming Language :: Python :: 3.12
Classifier: Programming Language :: Python :: 3.13
Classifier: Topic :: Scientific/Engineering :: Artificial Intelligence
Classifier: Topic :: Software Development :: Libraries :: Python Modules
Requires-Python: >=3.8
License-File: LICENSE
Requires-Dist: b64tensors>=0.2.0
Dynamic: license-file
